pyzxcvbn/__init__.py
pyzxcvbn/adjacency_graphs.py
pyzxcvbn/feedback.py
pyzxcvbn/frequency_lists.py
pyzxcvbn/main.py
pyzxcvbn/matching.py
pyzxcvbn/scoring.py
pyzxcvbn/time_estimates.py
pyzxcvbn-0.8.0.dist-info/DESCRIPTION.rst
pyzxcvbn-0.8.0.dist-info/METADATA
pyzxcvbn-0.8.0.dist-info/RECORD
pyzxcvbn-0.8.0.dist-info/WHEEL
pyzxcvbn-0.8.0.dist-info/metadata.json
pyzxcvbn-0.8.0.dist-info/top_level.txt
