Metadata-Version: 1.0
Name: pyzxcvbn
Version: 0.8.0
Summary: UNKNOWN
Home-page: https://github.com/taxpon/pyzxcvbn
Author: Takuro Wada
Author-email: taxpon@gmail.com
License: MIT
Platform: UNKNOWN
